cli/__init__.py
cli/config_generator.py
cli/consts.py
cli/core.py
cli/defaults.py
cli/docker_cli.py
cli/logo.py
cli/main.py
cli/merger.py
cli/models.py
cli/parser.py
cli/utils.py
cli/validator.py
cli/commands/__init__.py
cli/commands/config.py
cli/commands/generate.py
cli/commands/init.py
cli/commands/serve.py
cli/commands/show_config.py
cli/commands/show_defaults.py
cli/commands/validate.py
cli/templates/config.template.yaml
cli/templates/envoy.template.yaml
cli/templates/router-defaults.yaml
cli/templates/tools_db.json
vllm_sr-0.1.0rc7.dist-info/METADATA
vllm_sr-0.1.0rc7.dist-info/WHEEL
vllm_sr-0.1.0rc7.dist-info/entry_points.txt
vllm_sr-0.1.0rc7.dist-info/top_level.txt
vllm_sr-0.1.0rc7.dist-info/RECORD
