Metadata-Version: 2.4
Name: vllm-sr
Version: 0.1.0rc7
Summary: vLLM Semantic Router - Intelligent routing for Mixture-of-Models
Author: vLLM-SR Team
License: Apache-2.0
Project-URL: Homepage, https://github.com/vllm-project/vllm-semantic-router
Project-URL: Documentation, https://github.com/vllm-project/vllm-semantic-router/blob/main/README.md
Project-URL: Repository, https://github.com/vllm-project/vllm-semantic-router
Project-URL: Issues, https://github.com/vllm-project/vllm-semantic-router/issues
Keywords: vllm,semantic-router,llm,routing,caching
Classifier: Development Status :: 4 - Beta
Classifier: Intended Audience :: Developers
Classifier: License :: OSI Approved :: Apache Software License
Classifier: Programming Language :: Python :: 3
Classifier: Programming Language :: Python :: 3.10
Classifier: Programming Language :: Python :: 3.11
Classifier: Programming Language :: Python :: 3.12
Requires-Python: >=3.10
Requires-Dist: click>=8.1.7
Requires-Dist: pyyaml>=6.0.2
Requires-Dist: jinja2>=3.1.4
Requires-Dist: requests>=2.31.0
Requires-Dist: pydantic>=2.0.0
Requires-Dist: huggingface_hub[cli]>=0.20.0
Provides-Extra: dev
Requires-Dist: pytest>=8.4.1; extra == "dev"
Requires-Dist: black>=22.0.0; extra == "dev"
